{"chunk_definitions":[{"row":32,"row_count":1,"visible":true,"expansion_state":0,"options":{"engine":"r","message":false,"warning":false,"label":"unnamed-chunk-329"},"document_id":"66A14DE0","chunk_id":"cscetsvbcqj2m","chunk_label":"unnamed-chunk-1"},{"row":39,"row_count":1,"visible":true,"expansion_state":0,"options":{"engine":"r","message":false,"warning":false,"label":"unnamed-chunk-330"},"document_id":"66A14DE0","chunk_id":"c8ni1x8eov18w","chunk_label":"unnamed-chunk-2"},{"row":62,"row_count":1,"visible":true,"expansion_state":0,"options":{"engine":"r","label":"unnamed-chunk-331"},"document_id":"66A14DE0","chunk_id":"csqq2d6rkbxyt","chunk_label":"unnamed-chunk-3"},{"row":101,"row_count":1,"visible":true,"expansion_state":0,"options":{"engine":"r","warning":false,"label":"unnamed-chunk-334"},"document_id":"66A14DE0","chunk_id":"cz8r225fiihbv","chunk_label":"unnamed-chunk-4"},{"row":139,"row_count":1,"visible":true,"expansion_state":0,"options":{"engine":"r","warning":false,"label":"unnamed-chunk-354"},"document_id":"66A14DE0","chunk_id":"ccgs4ejoylrq3","chunk_label":"unnamed-chunk-5"}],"doc_write_time":1681392175}